infi.django_postgresql_migrations-0.3-py2.7-nspkg.pth
infi/django_postgresql_migrations/__init__.py
infi/django_postgresql_migrations/__version__.py
infi/django_postgresql_migrations/operations.py
infi.django_postgresql_migrations-0.3.dist-info/DESCRIPTION.rst
infi.django_postgresql_migrations-0.3.dist-info/METADATA
infi.django_postgresql_migrations-0.3.dist-info/RECORD
infi.django_postgresql_migrations-0.3.dist-info/WHEEL
infi.django_postgresql_migrations-0.3.dist-info/entry_points.txt
infi.django_postgresql_migrations-0.3.dist-info/metadata.json
infi.django_postgresql_migrations-0.3.dist-info/namespace_packages.txt
infi.django_postgresql_migrations-0.3.dist-info/top_level.txt
tests/__init__.py
tests/sample_project/__init__.py
tests/sample_project/fabfile.py
tests/sample_project/manage.py
tests/sample_project/settings.py
tests/sample_project/urls.py
tests/sample_project/wsgi.py
tests/sample_project/sample_app/__init__.py
tests/sample_project/sample_app/admin.py
tests/sample_project/sample_app/models.py
tests/sample_project/sample_app/tests.py
tests/sample_project/sample_app/views.py
tests/sample_project/sample_app/migrations/0001_initial.py
tests/sample_project/sample_app/migrations/0002_create_compact_index.py
tests/sample_project/sample_app/migrations/0003_create_trigram_index.py
tests/sample_project/sample_app/migrations/0004_set_statistics.py
tests/sample_project/sample_app/migrations/__init__.py
