Metadata-Version: 2.0
Name: infi.django-postgresql-migrations
Version: 0.3
Summary: Custom Django migration operations for PostgreSQL
Home-page: https://git.infinidat.com/host-opensource/infi.django_postgresql_migrations
Author: Itai Shirav
Author-email: itais@infinidat.com
License: PSF
Platform: UNKNOWN
Classifier: Intended Audience :: Developers
Classifier: Intended Audience :: System Administrators
Classifier: License :: OSI Approved :: Python Software Foundation License
Classifier: Operating System :: OS Independent
Classifier: Programming Language :: Python
Classifier: Topic :: Software Development :: Libraries :: Python Modules
Requires-Dist: setuptools
